woolly/__init__.py
woolly/__main__.py
woolly/cache.py
woolly/debug.py
woolly/http.py
woolly/progress.py
woolly/commands/__init__.py
woolly/commands/check.py
woolly/commands/clear_cache.py
woolly/commands/list_formats.py
woolly/commands/list_languages.py
woolly/languages/__init__.py
woolly/languages/base.py
woolly/languages/python.py
woolly/languages/rust.py
woolly/reporters/__init__.py
woolly/reporters/base.py
woolly/reporters/json.py
woolly/reporters/markdown.py
woolly/reporters/stdout.py
woolly/reporters/template.py
woolly-0.4.0.dist-info/METADATA
woolly-0.4.0.dist-info/WHEEL
woolly-0.4.0.dist-info/entry_points.txt
woolly-0.4.0.dist-info/licenses/LICENSE
woolly-0.4.0.dist-info/RECORD
