Metadata-Version: 2.4
Name: woolly
Version: 0.4.0
Summary: Check if package dependencies are available in Fedora. Supports Rust, Python, and more.
Author-email: Rodolfo Olivieri <rodolfo.olivieri3@gmail.com>
License-File: LICENSE
Classifier: Development Status :: 2 - Pre-Alpha
Classifier: Environment :: Console
Classifier: Intended Audience :: Developers
Classifier: Intended Audience :: Information Technology
Classifier: Intended Audience :: System Administrators
Classifier: License :: OSI Approved :: MIT License
Classifier: Natural Language :: English
Classifier: Operating System :: POSIX :: Linux
Classifier: Programming Language :: Python :: 3
Classifier: Programming Language :: Python :: 3 :: Only
Classifier: Programming Language :: Python :: 3.10
Classifier: Programming Language :: Python :: 3.11
Classifier: Programming Language :: Python :: 3.12
Classifier: Programming Language :: Python :: 3.13
Classifier: Programming Language :: Python :: 3.14
Classifier: Topic :: System :: Systems Administration
Classifier: Topic :: Utilities
Requires-Python: >=3.10
Requires-Dist: cyclopts>=4.3.0
Requires-Dist: httpx>=0.28.0
Requires-Dist: pydantic>=2.10.0
Requires-Dist: rich>=14.2.0
Provides-Extra: template
Requires-Dist: jinja2>=3.1.0; extra == 'template'
